{
  "id": "rdim4ps",
  "display_name": "Apnea-Hypopnea Index (Supine): (Apneas with >= 4% oxygen desaturation threshold used and with or without arousal+ hypopneas with > 50% flow reduction and with >= 4% oxygen desaturation used and with or without arousal) / hour of sleep in supine from type I polysomnography",
  "description": "[(total number of apneas and hypopneas in supine body position associated with >= 3% desaturation) / (hours of sleep)]. will be missing if no time supine or low position sensor quality.",
  "type": "numeric",
  "units": "events per hour",
  "calculation": "60*(hrembp4 + hnrbp4 + carbp4 + canbp4 + oarbp4 + oanbp4 + marbp4 + manrbp4)/(remepbp+nremepbp)",
  "labels": [
    "ahi_pb_ap4uhp5x4u_f1t1"
  ]
}
